{
  "KJ": {
    "TAMAN JAYA||KLCC": 3.1,
    "KLCC||TAMAN JAYA": 3.1,
    "GOMBAK||PUTRA HEIGHTS": 6.2,
    "PUTRA HEIGHTS||GOMBAK": 6.2,
    "WANGSA MAJU||USJ 7": 4.9,
    "USJ 7||WANGSA MAJU": 4.9,
    "TAMAN PARAMOUNT||SS 15": 2.9,
    "SS 15||TAMAN PARAMOUNT": 2.9,
    "JELATEK||WAWASAN": 4.4,
    "WAWASAN||JELATEK": 4.4,
    "KL SENTRAL-REDONE||TAMAN MELATI": 3.8,
    "TAMAN MELATI||KL SENTRAL-REDONE": 3.8,
    "GOMBAK||PASAR SENI": 3.9,
    "PASAR SENI||GOMBAK": 3.9,
    "SUBANG ALAM||AMPANG PARK": 4.7,
    "AMPANG PARK||SUBANG ALAM": 4.7,
    "PUTRA HEIGHTS||UNIVERSITI": 3.7,
    "UNIVERSITI||PUTRA HEIGHTS": 3.7,
    "KERINCHI||KLCC": 2.9,
    "KLCC||KERINCHI": 2.9,
    "ASIA JAYA||KERINCHI": 1.9,
    "KERINCHI||ASIA JAYA": 1.9,
    "TAMAN BAHAGIA||KAMPUNG BARU-CBP COOPBANK PERTAMA": 3.6,
    "KAMPUNG BARU-CBP COOPBANK PERTAMA||TAMAN BAHAGIA": 3.6,
    "USJ21||SS18": 2.2,
    "SS18||USJ21": 2.2,
    "TAIPAN||CGC GLENMARIE": 2.6,
    "CGC GLENMARIE||TAIPAN": 2.6,
    "ARA DAMANSARA||SRI RAMPAI": 3.8,
    "SRI RAMPAI||ARA DAMANSARA": 3.8,
    "ALAM MEGAH||BANK RAKYAT BANGSAR": 3.6,
    "BANK RAKYAT BANGSAR||ALAM MEGAH": 3.6,
    "ALAM MEGAH||USJ 7": 2.2,
    "USJ 7||ALAM MEGAH": 2.2,
    "LEMBAH SUBANG||PASAR SENI": 3.5,
    "PASAR SENI||LEMBAH SUBANG": 3.5,
    "DANG WANGI||PUTRA HEIGHTS": 4.5,
    "PUTRA HEIGHTS||DANG WANGI": 4.5,
    "DATO KERAMAT||TAIPAN": 4.2,
    "TAIPAN||DATO KERAMAT": 4.2
  },
  "SP": {
    "PUTRA HEIGHTS||PUSAT BANDAR PUCHONG": 2.9,
    "PUSAT BANDAR PUCHONG||PUTRA HEIGHTS": 2.9,
    "KINRARA||AWAN BESAR": 1.9,
    "AWAN BESAR||KINRARA": 1.9,
    "PUDU||MASJID JAMEK": 1.6,
    "MASJID JAMEK||PUDU": 1.6,
    "PWTC||SENTUL TIMUR": 1.5,
    "SENTUL TIMUR||PWTC": 1.5,
    "MUHIBBAH||BANDAR TASIK SELATAN": 2.7,
    "BANDAR TASIK SELATAN||MUHIBBAH": 2.7,
    "BANDARAYA-UOB||CHAN SOW LIN": 1.9,
    "CHAN SOW LIN||BANDARAYA-UOB": 1.9,
    "PUTRA HEIGHTS||SENTUL TIMUR": 4.9,
    "SENTUL TIMUR||PUTRA HEIGHTS": 4.9,
    "SUNGAI BESI||HANG TUAH": 3.1,
    "HANG TUAH||SUNGAI BESI": 3.1,
    "PUCHONG PERDANA||PWTC": 4.2,
    "PWTC||PUCHONG PERDANA": 4.2,
    "IOI PUCHONG JAYA||SALAK SELATAN": 3.8,
    "SALAK SELATAN||IOI PUCHONG JAYA": 3.8,
    "PUTRA HEIGHTS||SALAK SELATAN": 3.7,
    "SALAK SELATAN||PUTRA HEIGHTS": 3.7,
    "BUKIT JALIL||PUCHONG PERDANA": 3.5,
    "PUCHONG PERDANA||BUKIT JALIL": 3.5,
    "SENTUL||SENTUL TIMUR": 1.1,
    "SENTUL TIMUR||SENTUL": 1.1,
    "PUCHONG PERDANA||CHERAS": 4.2,
    "CHERAS||PUCHONG PERDANA": 4.2,
    "PUDU||PUCHONG PRIMA": 3.9,
    "PUCHONG PRIMA||PUDU": 3.9,
    "TAMAN PERINDUSTRIAN PUCHONG||PUDU": 4.3,
    "PUDU||TAMAN PERINDUSTRIAN PUCHONG": 4.3,
    "MUHIBBAH||PUDU": 3.6,
    "PUDU||MUHIBBAH": 3.6,
    "TITIWANGSA||MASJID JAMEK": 1.7,
    "MASJID JAMEK||TITIWANGSA": 1.7,
    "AWAN BESAR||BANDAR PUTERI": 3.1,
    "BANDAR PUTERI||AWAN BESAR": 3.1,
    "CHAN SOW LIN||PWTC": 2.3,
    "PWTC||CHAN SOW LIN": 2.3
  },
  "AG": {
    "AMPANG||MALURI": 2.1,
    "MALURI||AMPANG": 2.1,
    "AMPANG||PLAZA RAKYAT": 3,
    "PLAZA RAKYAT||AMPANG": 3,
    "PWTC||PLAZA RAKYAT": 1.7,
    "PLAZA RAKYAT||PWTC": 1.7,
    "SENTUL||SULTAN ISMAIL": 1.5,
    "SULTAN ISMAIL||SENTUL": 1.5,
    "PANDAN INDAH||MASJID JAMEK": 2.9,
    "MASJID JAMEK||PANDAN INDAH": 2.9,
    "PUDU||HANG TUAH": 1.1,
    "HANG TUAH||PUDU": 1.1,
    "CHAN SOW LIN||PWTC": 2.3,
    "PWTC||CHAN SOW LIN": 2.3,
    "SENTUL TIMUR||PWTC": 1.5,
    "PWTC||SENTUL TIMUR": 1.5,
    "MIHARJA||CEMPAKA": 2,
    "CEMPAKA||MIHARJA": 2,
    "MASJID JAMEK||SULTAN ISMAIL": 1.2,
    "SULTAN ISMAIL||MASJID JAMEK": 1.2,
    "AMPANG||BANDARAYA-UOB": 3.3,
    "BANDARAYA-UOB||AMPANG": 3.3,
    "CAHAYA||TITIWANGSA": 3.5,
    "TITIWANGSA||CAHAYA": 3.5,
    "PANDAN JAYA||TITIWANGSA": 3,
    "TITIWANGSA||PANDAN JAYA": 3,
    "SULTAN ISMAIL||PANDAN JAYA": 3,
    "PANDAN JAYA||SULTAN ISMAIL": 3,
    "CAHAYA||CEMPAKA": 0.9,
    "CEMPAKA||CAHAYA": 0.9,
    "MALURI||PANDAN JAYA": 1.3,
    "PANDAN JAYA||MALURI": 1.3,
    "MIHARJA||CHAN SOW LIN": 1.1,
    "CHAN SOW LIN||MIHARJA": 1.1,
    "PLAZA RAKYAT||CHAN SOW LIN": 1.6,
    "CHAN SOW LIN||PLAZA RAKYAT": 1.6,
    "PWTC||PANDAN INDAH": 3.1,
    "PANDAN INDAH||PWTC": 3.1,
    "PUDU||PANDAN INDAH": 2.3,
    "PANDAN INDAH||PUDU": 2.3
  },
  "MRT": {
    "KWASA DAMANSARA||KWASA SENTRAL": 1.2,
    "KWASA SENTRAL||KWASA DAMANSARA": 1.2,
    "KWASA SENTRAL||KOTA DAMANSARA": 1.7,
    "KOTA DAMANSARA||KWASA SENTRAL": 1.7,
    "KOTA DAMANSARA||SURIAN": 1.3,
    "SURIAN||KOTA DAMANSARA": 1.3,
    "SURIAN||MUTIARA DAMANSARA": 1.4,
    "MUTIARA DAMANSARA||SURIAN": 1.4,
    "MUTIARA DAMANSARA||BANDAR UTAMA": 1.3,
    "BANDAR UTAMA||MUTIARA DAMANSARA": 1.3,
    "BANDAR UTAMA||TAMAN TUN DR ISMAIL": 1.4,
    "TAMAN TUN DR ISMAIL||BANDAR UTAMA": 1.4,
    "TAMAN TUN DR ISMAIL||PHILEO DAMANSARA": 1.3,
    "PHILEO DAMANSARA||TAMAN TUN DR ISMAIL": 1.3,
    "PHILEO DAMANSARA||PUSAT BANDAR DAMANSARA": 1.7,
    "PUSAT BANDAR DAMANSARA||PHILEO DAMANSARA": 1.7,
    "PUSAT BANDAR DAMANSARA||SEMANTAN": 1.6,
    "SEMANTAN||PUSAT BANDAR DAMANSARA": 1.6,
    "SEMANTAN||MUZIUM NEGARA": 1.3,
    "MUZIUM NEGARA||SEMANTAN": 1.3,
    "MUZIUM NEGARA||PASAR SENI": 1.2,
    "PASAR SENI||MUZIUM NEGARA": 1.2,
    "PASAR SENI||MERDEKA": 1,
    "MERDEKA||PASAR SENI": 1,
    "MERDEKA||BUKIT BINTANG": 1.2,
    "BUKIT BINTANG||MERDEKA": 1.2,
    "BUKIT BINTANG||TRX": 1.2,
    "TRX||BUKIT BINTANG": 1.2,
    "TRX||COCHRANE": 1.2,
    "COCHRANE||TRX": 1.2,
    "COCHRANE||MALURI": 1.1,
    "MALURI||COCHRANE": 1.1,
    "MALURI||TAMAN PERTAMA": 1.3,
    "TAMAN PERTAMA||MALURI": 1.3,
    "TAMAN PERTAMA||TAMAN MIDAH": 1.1,
    "TAMAN MIDAH||TAMAN PERTAMA": 1.1,
    "TAMAN MIDAH||TAMAN MUTIARA": 1.3,
    "TAMAN MUTIARA||TAMAN MIDAH": 1.3,
    "TAMAN MUTIARA||TAMAN CONNAUGHT": 1.3,
    "TAMAN CONNAUGHT||TAMAN MUTIARA": 1.3,
    "KWASA DAMANSARA||BANDAR UTAMA": 2.9,
    "BANDAR UTAMA||KWASA DAMANSARA": 2.9,
    "KWASA DAMANSARA||MERDEKA": 4.1,
    "MERDEKA||KWASA DAMANSARA": 4.1,
    "KWASA DAMANSARA||TAMAN PERTAMA": 4,
    "TAMAN PERTAMA||KWASA DAMANSARA": 4,
    "KWASA DAMANSARA||BANDAR TUN HUSSEIN ONN": 5,
    "BANDAR TUN HUSSEIN ONN||KWASA DAMANSARA": 5,
    "KWASA DAMANSARA||STADIUM KAJANG": 5.8,
    "STADIUM KAJANG||KWASA DAMANSARA": 5.8
  },
  "PYL": {
    "KWASA DAMANSARA||PUTRAJAYA SENTRAL": 6.9,
    "PUTRAJAYA SENTRAL||KWASA DAMANSARA": 6.9,
    "KWASA DAMANSARA||DAMANSARA DAMAI": 2.2,
    "DAMANSARA DAMAI||KWASA DAMANSARA": 2.2,
    "SUNGAI BULOH||SRI DAMANSARA SENTRAL": 2.1,
    "SRI DAMANSARA SENTRAL||SUNGAI BULOH": 2.1,
    "TITIWANGSA||METRO PRIMA": 3.2,
    "METRO PRIMA||TITIWANGSA": 3.2,
    "METRO PRIMA||TUN RAZAK EXCHANGE": 3.5,
    "TUN RAZAK EXCHANGE||METRO PRIMA": 3.5,
    "TUN RAZAK EXCHANGE||JINJANG": 3.6,
    "JINJANG||TUN RAZAK EXCHANGE": 3.6,
    "KAMPUNG SELAMAT||CHAN SOW LIN": 3.6,
    "CHAN SOW LIN||KAMPUNG SELAMAT": 3.6,
    "CONLAY||HOSPITAL KUALA LUMPUR": 1.9,
    "HOSPITAL KUALA LUMPUR||CONLAY": 1.9,
    "SERDANG JAYA||KENTOMEN": 3.5,
    "KENTOMEN||SERDANG JAYA": 3.5,
    "SUNGAI BESI||TAMAN NAGA EMAS": 1.4,
    "TAMAN NAGA EMAS||SUNGAI BESI": 1.4,
    "RAJA UDA||UPM": 3.9,
    "UPM||RAJA UDA": 3.9,
    "CYBERJAYA CITY CENTRE||16 SIERRA": 1.8,
    "16 SIERRA||CYBERJAYA CITY CENTRE": 1.8,
    "PUTRAJAYA SENTRAL||CYBERJAYA CITY CENTRE": 1.2,
    "CYBERJAYA CITY CENTRE||PUTRAJAYA SENTRAL": 1.2,
    "TAMAN EQUINE||CONLAY": 4.2,
    "CONLAY||TAMAN EQUINE": 4.2,
    "PUTRA PERMAI||AMPANG PARK": 3.7,
    "AMPANG PARK||PUTRA PERMAI": 3.7,
    "KAMPUNG BATU||JALAN IPOH": 1.4,
    "JALAN IPOH||KAMPUNG BATU": 1.4,
    "SUNGAI BULOH||PERSIARAN KLCC": 3.9,
    "PERSIARAN KLCC||SUNGAI BULOH": 3.9,
    "SRI DAMANSARA TIMUR||SERDANG RAYA UTARA": 4,
    "SERDANG RAYA UTARA||SRI DAMANSARA TIMUR": 4,
    "DAMANSARA DAMAI||PUTRA PERMAI": 5.7,
    "PUTRA PERMAI||DAMANSARA DAMAI": 5.7,
    "SUNGAI BESI||RAJA UDA": 3.9,
    "RAJA UDA||SUNGAI BESI": 3.9
  },
  "MR": {
    "KL SENTRAL||TUN SAMBANTHAN": 1.3,
    "TUN SAMBANTHAN||KL SENTRAL": 1.3,
    "KL SENTRAL||MAHARAJALELA": 2.2,
    "MAHARAJALELA||KL SENTRAL": 2.2,
    "KL SENTRAL||HANG TUAH": 2.8,
    "HANG TUAH||KL SENTRAL": 2.8,
    "KL SENTRAL||IMBI": 3.1,
    "IMBI||KL SENTRAL": 3.1,
    "KL SENTRAL||BUKIT BINTANG": 2.5,
    "BUKIT BINTANG||KL SENTRAL": 2.5,
    "MAHARAJALELA||BUKIT BINTANG": 2.2,
    "BUKIT BINTANG||MAHARAJALELA": 2.2,
    "MAHARAJALELA||BUKIT NANAS": 3.1,
    "BUKIT NANAS||MAHARAJALELA": 3.1,
    "MAHARAJALELA||MEDAN TUANKU": 2.6,
    "MEDAN TUANKU||MAHARAJALELA": 2.6,
    "MAHARAJALELA||CHOW KIT": 2.9,
    "CHOW KIT||MAHARAJALELA": 2.9,
    "MAHARAJALELA||TITIWANGSA": 2.7,
    "TITIWANGSA||MAHARAJALELA": 2.7
  },
  "BRT": {
    "SUNWAY-SETIA JAYA||SUNMED": 2.9,
    "SUNMED||SUNWAY-SETIA JAYA": 2.9,
    "USJ7||SUNWAY LAGOON": 4,
    "SUNWAY LAGOON||USJ7": 4,
    "SUNU-MONASH||SUNWAY LAGOON": 2.3,
    "SUNWAY LAGOON||SUNU-MONASH": 2.3,
    "SOUTH QUAY-USJ 1||MENTARI": 3.8,
    "MENTARI||SOUTH QUAY-USJ 1": 3.8,
    "SUNWAY-SETIA JAYA||USJ 7": 5.3,
    "USJ 7||SUNWAY-SETIA JAYA": 5.3,
    "SUNMED||SOUTH QUAY-USJ 1": 2.5,
    "SOUTH QUAY-USJ 1||SUNMED": 2.5,
    "MENTARI||SUNU-MONASH": 2.9,
    "SUNU-MONASH||MENTARI": 2.9,
    "MENTARI||SUNWAY-SETIA JAYA": 1.6,
    "SUNWAY-SETIA JAYA||MENTARI": 1.6,
    "SUNWAY LAGOON||SUNWAY-SETIA JAYA": 2.2,
    "SUNWAY-SETIA JAYA||SUNWAY LAGOON": 2.2,
    "SUNWAY LAGOON||USJ 7": 4,
    "USJ 7||SUNWAY LAGOON": 4
  }
}